Metadata-Version: 1.0
Name: faker-ids
Version: 0.0.9
Summary: Fake id generator. Fetches upto 5 MILLION fake details like firstname, lastnam, emailid and mobile number.
Home-page: UNKNOWN
Author: Balaji Betadur
Author-email: balajibetadur@gmail.com
License: MIT
Keywords: fakeid,indians,indian fake ids,faker,fakes,fake ids,python,fake-ids python,fake indian ids python
Platform: UNKNOWN
